APIManager-DM-2024/__init__.py
APIManager-DM-2024/main.py
api_manager/__init__.py
api_manager/main.py
APIManager_DM_2024-0.1.1.dist-info/METADATA
APIManager_DM_2024-0.1.1.dist-info/WHEEL
APIManager_DM_2024-0.1.1.dist-info/top_level.txt
APIManager_DM_2024-0.1.1.dist-info/RECORD
