Metadata-Version: 2.1
Name: APIManager-DM-2024
Version: 0.1.1
Home-page: https://github.com/movsdav/APIManager_DM_2024
Requires-Dist: requests >=2.31.0
